[
    {
        "id": "1",
        "title": "فوز فريق البشائر ببطولة المنطقة",
        "content": "حقق فريق أكاديمية البشائر فوزاً مستحقاً ببطولة المنطقة للناشئين بعد أداء متميز طوال البطولة.",
        "image": "",
        "date": "2024-12-10",
        "isPublished": true
    },
    {
        "id": "2",
        "title": "انطلاق التسجيل للموسم الجديد",
        "content": "نعلن عن فتح باب التسجيل للموسم التدريبي الجديد. سارعوا بتسجيل أبنائكم!",
        "image": "",
        "date": "2024-12-01",
        "isPublished": true
    }
]
